[{"comment_id":"630903010433611","commenter_b":"Get her out of the White House!!","commenter_a":"out of her mind !!!!!","post_message":"Michelle Obama is trying to close all American museums for this absurd reason. She is a racist. This is complete madness. Do you think Michelle Obama is out of her mind?"},{"comment_id":"861460177233384","commenter_b":"She needs to smoke. Nancy Disgrace","commenter_a":"I refuse to watch her anymore..go away Nancy!!!!","post_message":"Nancy Grace vs. 2 Chainz: Part 2! Right now on HLN. Where do you stand on the debate? #PotToBlame"},{"comment_id":"10156209671355354","commenter_b":"Please stay there! Not welcome in Texas!","commenter_a":"I hope the next administration is one that will take this down!!","post_message":"And look what it's expected to be by 2018!"},{"comment_id":"10153852304249160","commenter_b":"Trump deport this foreigner","commenter_a":"Obama and Hillary need to get out of Washington & Politics period!..both are criminals and traitors to the American people!.they can take that communist Sanders with them. Trump 2016","post_message":"Hillary Clinton's numbers are collapsing."},{"comment_id":"10153772983356813","commenter_b":"Does that mean pardoning him for his rape accusation that he fled the country for as well?","commenter_a":"Snowden deserves a pardon. More than Obama deserves to be POTUS.","post_message":"Now's the time for Barack Obama to pardon Snowden."},{"comment_id":"10153264215531051","commenter_b":"prison is to good for thay bitch","commenter_a":"How about in her not taking care of an American ambassador in Bengazi","post_message":"Question: Do you think Hillary Clinton is guilty of criminal wrongdoing in her email scandal?"},{"comment_id":"10154777033398128","commenter_b":"Are you jealous?","commenter_a":"Elvira Jaha","post_message":"London Calling: The U.K. has become the cheapest market in the world for luxury goods."}]
